jssapi/__init__.py
jssapi/cli.py
jssapi/cph.py
jssapi/decorators.py
jssapi/jssapi.py
jssapi-0.2.0.dist-info/DESCRIPTION.rst
jssapi-0.2.0.dist-info/METADATA
jssapi-0.2.0.dist-info/RECORD
jssapi-0.2.0.dist-info/WHEEL
jssapi-0.2.0.dist-info/entry_points.txt
jssapi-0.2.0.dist-info/metadata.json
jssapi-0.2.0.dist-info/top_level.txt
