Metadata-Version: 2.0
Name: jssapi
Version: 0.2.0
Summary: Provide API calls for jamf Pro (formerly JSS)
Home-page: https://github.com/sreyemnayr/jamf_pro_api
Author: Ryan Meyers
Author-email: ryanmeyersweb@gmail.com
License: MIT license
Keywords: jssapi
Platform: UNKNOWN
Classifier: Development Status :: 2 - Pre-Alpha
Classifier: Intended Audience :: Developers
Classifier: License :: OSI Approved :: MIT License
Classifier: Natural Language :: English
Classifier: Programming Language :: Python :: 2
Classifier: Programming Language :: Python :: 2.7
Classifier: Programming Language :: Python :: 3
Classifier: Programming Language :: Python :: 3.6
Requires-Dist: Click (>=6.0)
Requires-Dist: SQLAlchemy (>=1.2.2)
